idiolect/__init__.py
idiolect/idioms.py
idiolect-0.0.0.dev1.dist-info/METADATA
idiolect-0.0.0.dev1.dist-info/WHEEL
idiolect-0.0.0.dev1.dist-info/entry_points.txt
idiolect-0.0.0.dev1.dist-info/RECORD
