Metadata-Version: 2.4
Name: idiolect
Version: 0.0.0.dev1
Summary: Add your description here
Author-email: kosmolebryce <k.lebryce@pm.me>
Requires-Python: >=3.12.8
Requires-Dist: python-dotenv>=1.1.0
